scml/__init__.py
scml/__main__.py
scml/cli.py
scml/cliadv.py
scml/common.py
scml/experiment.py
scml/runner.py
scml/utils.py
scml/oneshot/__init__.py
scml/oneshot/adapter.py
scml/oneshot/agent.py
scml/oneshot/awi.py
scml/oneshot/common.py
scml/oneshot/context.py
scml/oneshot/helper.py
scml/oneshot/mixins.py
scml/oneshot/policy.py
scml/oneshot/sysagents.py
scml/oneshot/ufun.py
scml/oneshot/world.py
scml/oneshot/agents/__init__.py
scml/oneshot/agents/aspiration.py
scml/oneshot/agents/greedy.py
scml/oneshot/agents/nothing.py
scml/oneshot/agents/rand.py
scml/oneshot/rl/__init__.py
scml/oneshot/rl/action.py
scml/oneshot/rl/agent.py
scml/oneshot/rl/common.py
scml/oneshot/rl/env.py
scml/oneshot/rl/helpers.py
scml/oneshot/rl/observation.py
scml/oneshot/rl/policies.py
scml/oneshot/rl/reward.py
scml/scml2019/__init__.py
scml/scml2019/agent.py
scml/scml2019/awi.py
scml/scml2019/bank.py
scml/scml2019/common.py
scml/scml2019/consumers.py
scml/scml2019/helpers.py
scml/scml2019/insurance.py
scml/scml2019/miners.py
scml/scml2019/schedulers.py
scml/scml2019/simulators.py
scml/scml2019/utils19.py
scml/scml2019/visualizers.py
scml/scml2019/world.py
scml/scml2019/factory_managers/__init__.py
scml/scml2019/factory_managers/builtins.py
scml/scml2020/__init__.py
scml/scml2020/agent.py
scml/scml2020/awi.py
scml/scml2020/common.py
scml/scml2020/factory.py
scml/scml2020/world.py
scml/scml2020/agents/__init__.py
scml/scml2020/agents/bcse.py
scml/scml2020/agents/decentralizing.py
scml/scml2020/agents/do_nothing.py
scml/scml2020/agents/indneg.py
scml/scml2020/agents/moving.py
scml/scml2020/agents/random.py
scml/scml2020/agents/reactive.py
scml/scml2020/agents/satisficer.py
scml/scml2020/components/__init__.py
scml/scml2020/components/negotiation.py
scml/scml2020/components/prediction.py
scml/scml2020/components/production.py
scml/scml2020/components/signing.py
scml/scml2020/components/simulation.py
scml/scml2020/components/trading.py
scml/scml2020/services/__init__.py
scml-0.7.7.dist-info/licenses/AUTHORS.rst
scml-0.7.7.dist-info/licenses/LICENSE
scml-0.7.7.dist-info/METADATA
scml-0.7.7.dist-info/WHEEL
scml-0.7.7.dist-info/entry_points.txt
scml-0.7.7.dist-info/top_level.txt
scml-0.7.7.dist-info/RECORD
