Metadata-Version: 2.4
Name: scml
Version: 0.7.7
Summary: ANAC Supply Chain Management League Platform
Home-page: https://github.com/yasserfarouk/scml
Author: Yasser Mohammad
Author-email: yasserfarouk@gmail.com
Project-URL: Documentation, https://scml.readthedocs.io/
Project-URL: Changelog, https://scml.readthedocs.io/en/latest/changelog.html
Project-URL: Issue Tracker, https://github.com/yasserfarouk/scml/issues
Classifier: Development Status :: 5 - Production/Stable
Classifier: Intended Audience :: Developers
Classifier: License :: OSI Approved :: GNU General Public License v2 or later (GPLv2+)
Classifier: Operating System :: Unix
Classifier: Operating System :: POSIX
Classifier: Operating System :: Microsoft :: Windows
Classifier: Programming Language :: Python
Classifier: Programming Language :: Python :: 3.10
Classifier: Programming Language :: Python :: 3.11
Classifier: Programming Language :: Python :: 3.12
Classifier: Programming Language :: Python :: Implementation :: CPython
Classifier: Programming Language :: Python :: Implementation :: PyPy
Requires-Python: >=3.10
License-File: LICENSE
License-File: AUTHORS.rst
Requires-Dist: click
Requires-Dist: click-aliases
Requires-Dist: pytest
Requires-Dist: hypothesis
Requires-Dist: negmas>=0.11.2
Requires-Dist: joblib
Requires-Dist: jupyter
Requires-Dist: gif
Requires-Dist: gymnasium
Provides-Extra: gui
Requires-Dist: pyqt5; extra == "gui"
Dynamic: author
Dynamic: author-email
Dynamic: classifier
Dynamic: description
Dynamic: description-content-type
Dynamic: home-page
Dynamic: license-file
Dynamic: project-url
Dynamic: provides-extra
Dynamic: requires-dist
Dynamic: requires-python
Dynamic: summary
